serverless_llm-0.8.0.dist-info/licenses/LICENSE
sllm/__init__.py
sllm/app_lib.py
sllm/controller.py
sllm/fine_tuning_instance.py
sllm/fine_tuning_job_store.py
sllm/hardware_info_collector.py
sllm/inference_instance.py
sllm/logger.py
sllm/model_downloader.py
sllm/store_manager.py
sllm/utils.py
sllm/backends/__init__.py
sllm/backends/backend_utils.py
sllm/backends/dummy_backend.py
sllm/backends/transformers_backend.py
sllm/backends/vllm_backend.py
sllm/cli/__init__.py
sllm/cli/_cli_utils.py
sllm/cli/clic.py
sllm/cli/default_config.json
sllm/ft_backends/__init__.py
sllm/ft_backends/backend_utils.py
sllm/ft_backends/peft_lora_backend.py
sllm/routers/__init__.py
sllm/routers/migration_router.py
sllm/routers/roundrobin_router.py
sllm/routers/router_utils.py
sllm/schedulers/__init__.py
sllm/schedulers/fcfs_scheduler.py
sllm/schedulers/scheduler_utils.py
sllm/schedulers/storage_aware_scheduler.py
tests/__init__.py
tests/conftest.py
tests/utils.py
serverless_llm-0.8.0.dist-info/METADATA
serverless_llm-0.8.0.dist-info/WHEEL
serverless_llm-0.8.0.dist-info/entry_points.txt
serverless_llm-0.8.0.dist-info/top_level.txt
serverless_llm-0.8.0.dist-info/RECORD
