Metadata-Version: 2.4
Name: serverless-llm
Version: 0.8.0
License-File: LICENSE
Requires-Dist: fastapi==0.115.12
Requires-Dist: GPUtil==1.4.0
Requires-Dist: openai==1.52.0
Requires-Dist: pydantic==2.11.5
Requires-Dist: pydantic_core==2.33.2
Requires-Dist: ray==2.46.0
Requires-Dist: requests==2.32.2
Requires-Dist: serverless-llm-store
Requires-Dist: speedtest-cli==2.1.3
Requires-Dist: types-requests==2.31.0.20240125
Requires-Dist: uvicorn[standard]==0.23.1
Provides-Extra: test
Requires-Dist: accelerate==1.7.0; extra == "test"
Requires-Dist: datasets==3.6.0; extra == "test"
Requires-Dist: GPUtil==1.4.0; extra == "test"
Requires-Dist: outlines==0.1.11; extra == "test"
Requires-Dist: peft==0.15.2; extra == "test"
Requires-Dist: ray==2.46.0; extra == "test"
Requires-Dist: speedtest-cli==2.1.3; extra == "test"
Requires-Dist: torch==2.7.0; extra == "test"
Requires-Dist: transformers==4.52.4; extra == "test"
Requires-Dist: vllm==0.9.0.1; extra == "test"
Requires-Dist: pytest; extra == "test"
Requires-Dist: pytest-asyncio; extra == "test"
Provides-Extra: worker
Requires-Dist: accelerate==1.7.0; extra == "worker"
Requires-Dist: datasets==3.6.0; extra == "worker"
Requires-Dist: GPUtil==1.4.0; extra == "worker"
Requires-Dist: outlines==0.1.11; extra == "worker"
Requires-Dist: peft==0.15.2; extra == "worker"
Requires-Dist: ray==2.46.0; extra == "worker"
Requires-Dist: speedtest-cli==2.1.3; extra == "worker"
Requires-Dist: torch==2.7.0; extra == "worker"
Requires-Dist: transformers==4.52.4; extra == "worker"
Requires-Dist: vllm==0.9.0.1; extra == "worker"
Dynamic: description
Dynamic: description-content-type
Dynamic: license-file
Dynamic: provides-extra
Dynamic: requires-dist
